odoo/addons/sale_subscription_partner_pricelist/LICENSE
odoo/addons/sale_subscription_partner_pricelist/README.rst
odoo/addons/sale_subscription_partner_pricelist/__init__.py
odoo/addons/sale_subscription_partner_pricelist/__manifest__.py
odoo/addons/sale_subscription_partner_pricelist/images/screen.png
odoo/addons/sale_subscription_partner_pricelist/models/__init__.py
odoo/addons/sale_subscription_partner_pricelist/models/res_partner.py
odoo/addons/sale_subscription_partner_pricelist/models/sale_order.py
odoo/addons/sale_subscription_partner_pricelist/static/description/icon.png
odoo/addons/sale_subscription_partner_pricelist/static/description/index.html
odoo/addons/sale_subscription_partner_pricelist/tests/TEST_INSTRUCTIONS.rst
odoo_addon_sale_subscription_partner_pricelist-18.0.1.0.0.dist-info/METADATA
odoo_addon_sale_subscription_partner_pricelist-18.0.1.0.0.dist-info/WHEEL
odoo_addon_sale_subscription_partner_pricelist-18.0.1.0.0.dist-info/top_level.txt
odoo_addon_sale_subscription_partner_pricelist-18.0.1.0.0.dist-info/RECORD
